home/subrata/.local/share/man/man1/webvid.1.gz
webvid/__init__.py
webvid/webvid_download.py
webvid/IPL/NewIPLDownloader.py
webvid/IPL/__init__.py
webvid/IPL/test.py
webvid/IPL/test1.py
webvid/PHUB/NewphubDownloader.py
webvid/PHUB/__init__.py
webvid/get_m3u8/__init__.py
webvid/get_m3u8/get_m3u8_link.py
webvid-0.0.7.dist-info/METADATA
webvid-0.0.7.dist-info/WHEEL
webvid-0.0.7.dist-info/entry_points.txt
webvid-0.0.7.dist-info/top_level.txt
webvid-0.0.7.dist-info/RECORD
